<HAS id="1">
  <player id="2"/>
  <room id="3"/>
  <song id="4">
    <song id="5">
      <name>Blood on the Leaves</name>
      <duration id="6">00:04:24</duration>
      <genre>Rap</genre>
      <trackNum>8</trackNum>
      <artist id="7">
        <name>Kanye</name>
        <album id="8">
          <album id="9">
            <name>Yeezus</name>
            <date id="10">2012-02-01</date>
            <song id="11">
              <null/>
              <song reference="5"/>
              <song id="12">
                <name>Black Skinhead</name>
                <duration id="13">00:03:22</duration>
                <genre>Rap</genre>
                <trackNum>8</trackNum>
                <artist reference="7"/>
              </song>
              <song id="14">
                <name>Yolo</name>
                <duration id="15">00:10:26</duration>
                <genre>Rocknroll</genre>
                <trackNum>6</trackNum>
                <artist reference="7"/>
              </song>
            </song>
            <artist reference="7"/>
          </album>
        </album>
        <songs id="16">
          <song reference="5"/>
          <song reference="12"/>
          <song reference="14"/>
        </songs>
      </artist>
    </song>
    <song reference="12"/>
    <song id="17">
      <name>My Dad&apos;s Gone Crazy</name>
      <duration id="18">00:05:22</duration>
      <genre>Rap</genre>
      <trackNum>7</trackNum>
      <artist id="19">
        <name>Eminem</name>
        <album id="20">
          <album id="21">
            <name>The Marshall Mathers LP</name>
            <date id="22">2001-01-01</date>
            <song id="23">
              <null/>
              <song id="24">
                <name>Drips</name>
                <duration id="25">00:02:55</duration>
                <genre>Rap</genre>
                <trackNum>1</trackNum>
                <artist reference="19"/>
              </song>
              <song reference="17"/>
              <song id="26">
                <name>Steve Berman Skit</name>
                <duration id="27">00:00:31</duration>
                <genre>Skit</genre>
                <trackNum>3</trackNum>
                <artist reference="19"/>
              </song>
              <song id="28">
                <name>Without Me</name>
                <duration id="29">00:05:22</duration>
                <genre>Rap</genre>
                <trackNum>6</trackNum>
                <artist reference="19"/>
              </song>
              <song id="30">
                <name>Till I Collapse</name>
                <duration id="31">00:05:23</duration>
                <genre>Rap</genre>
                <trackNum>4</trackNum>
                <artist reference="19"/>
              </song>
              <song id="32">
                <name>Say Goodbye to Hollywood</name>
                <duration id="33">00:04:21</duration>
                <genre>Rap</genre>
                <trackNum>6</trackNum>
                <artist reference="19"/>
              </song>
              <song id="34">
                <name>Say What You Say</name>
                <duration id="35">00:04:19</duration>
                <genre>Rap</genre>
                <trackNum>8</trackNum>
                <artist reference="19"/>
              </song>
            </song>
            <artist reference="19"/>
          </album>
        </album>
        <songs id="36">
          <song reference="17"/>
          <song reference="24"/>
          <song reference="28"/>
          <song id="37">
            <name>Say Goodbye to Hollywood</name>
            <duration id="38">00:04:21</duration>
            <genre>Rap</genre>
            <trackNum>5</trackNum>
            <artist reference="19"/>
          </song>
          <song reference="32"/>
          <song reference="30"/>
          <song reference="34"/>
          <song reference="26"/>
        </songs>
      </artist>
    </song>
    <song reference="24"/>
    <song reference="28"/>
    <song reference="32"/>
    <song reference="30"/>
    <song reference="34"/>
    <song reference="26"/>
    <song id="39">
      <name>The AfterParty</name>
      <duration id="40">00:04:00</duration>
      <genre>Rap</genre>
      <trackNum>7</trackNum>
      <artist id="41">
        <name>Childish Gambino</name>
        <album id="42">
          <album id="43">
            <name>Because the Internet</name>
            <date id="44">2013-03-18</date>
            <song id="45">
              <null/>
              <song reference="39"/>
            </song>
            <artist reference="41"/>
          </album>
        </album>
        <songs id="46">
          <song reference="39"/>
        </songs>
      </artist>
    </song>
    <song id="47">
      <name>Pumped Up Kicks</name>
      <duration id="48">00:04:22</duration>
      <genre>Indie</genre>
      <trackNum>5</trackNum>
      <artist id="49">
        <name>Foster The People</name>
        <album id="50">
          <album id="51">
            <name>Torches</name>
            <date id="52">2011-01-01</date>
            <song id="53">
              <null/>
              <song reference="47"/>
            </song>
            <artist reference="49"/>
          </album>
        </album>
        <songs id="54">
          <song reference="47"/>
        </songs>
      </artist>
    </song>
    <song id="55">
      <name>Hello</name>
      <duration id="56">00:04:55</duration>
      <genre>Rap</genre>
      <trackNum>8</trackNum>
      <artist id="57">
        <name>Test Artist</name>
        <album id="58">
          <album id="59">
            <name>Test Album</name>
            <date id="60">1997-03-02</date>
            <song id="61">
              <null/>
              <song reference="55"/>
              <song id="62">
                <name>You</name>
                <duration id="63">00:05:21</duration>
                <genre>Rap</genre>
                <trackNum>2</trackNum>
                <artist reference="57"/>
              </song>
            </song>
            <artist reference="57"/>
          </album>
          <album id="64">
            <name>SWOLO</name>
            <date id="65">2016-08-24</date>
            <song id="66">
              <song id="67">
                <name>Swag Yolo</name>
                <duration id="68">00:04:25</duration>
                <genre>RocknRoll</genre>
                <trackNum>9</trackNum>
                <artist reference="57"/>
              </song>
            </song>
            <artist reference="57"/>
          </album>
        </album>
        <songs id="69">
          <song reference="55"/>
          <song reference="62"/>
          <song reference="67"/>
        </songs>
      </artist>
    </song>
    <song reference="62"/>
    <song id="70">
      <name>Hello</name>
      <duration id="71">00:03:22</duration>
      <genre>Hi</genre>
      <trackNum>6</trackNum>
      <artist id="72">
        <name>Kanye West</name>
        <album id="73">
          <album id="74">
            <name>Kanye Is best</name>
            <date id="75">2016-03-23</date>
            <song id="76">
              <song reference="70"/>
            </song>
            <artist reference="72"/>
          </album>
        </album>
        <songs id="77">
          <song reference="70"/>
        </songs>
      </artist>
    </song>
    <song reference="67"/>
    <song reference="14"/>
    <song id="78">
      <name>wert,yu</name>
      <duration id="79">10:01:50</duration>
      <genre>qwert</genre>
      <trackNum>6</trackNum>
      <artist id="80">
        <name>tttttt</name>
        <album id="81">
          <album id="82">
            <name>dddddd</name>
            <date id="83">2016-03-17</date>
            <song id="84">
              <song reference="78"/>
            </song>
            <artist reference="80"/>
          </album>
        </album>
        <songs id="85">
          <song reference="78"/>
        </songs>
      </artist>
    </song>
  </song>
  <album id="86">
    <album reference="9"/>
    <album reference="21"/>
    <album reference="43"/>
    <album reference="51"/>
    <album reference="59"/>
    <album reference="74"/>
    <album reference="64"/>
    <album reference="82"/>
  </album>
  <playlist id="87">
    <model.Playlist id="88">
      <name>Super Fun Trax</name>
      <song id="89">
        <song reference="30"/>
        <song reference="55"/>
      </song>
    </model.Playlist>
    <model.Playlist id="90">
      <name>Hot Dope Traxxxx</name>
      <song id="91">
        <song reference="17"/>
        <song reference="5"/>
      </song>
    </model.Playlist>
    <model.Playlist id="92">
      <name>Boyakasha</name>
      <song id="93">
        <song reference="32"/>
      </song>
    </model.Playlist>
  </playlist>
  <artist id="94">
    <artist reference="7"/>
    <artist reference="19"/>
    <artist reference="41"/>
    <artist reference="49"/>
    <artist reference="57"/>
    <artist reference="72"/>
    <artist id="95">
      <name>Kanye West</name>
      <album id="96"/>
      <songs id="97"/>
    </artist>
    <artist id="98">
      <name>T Swizzle</name>
      <album id="99"/>
      <songs id="100"/>
    </artist>
    <artist reference="80"/>
  </artist>
</HAS>